{
  "roi": 11.32,
  "cycle": 142,
  "trades": 4738,
  "wr": 29.3,
  "grids": {
    "VVV": {
      "center": 11.518,
      "pnl": 23.48
    },
    "LIT": {
      "center": 2.4111,
      "pnl": -22.8
    },
    "GRASS": {
      "center": 0.47754,
      "pnl": -36.12
    },
    "WLD": {
      "center": 0.40276,
      "pnl": 63.03
    },
    "XPL": {
      "center": 0.10327,
      "pnl": 40.71
    },
    "EIGEN": {
      "center": 0.2209,
      "pnl": 65.85
    },
    "PUMP": {
      "center": 0.001559,
      "pnl": -20.94
    }
  },
  "pesos": {
    "VVV": 0.05,
    "LIT": 0.05,
    "GRASS": 0.05,
    "WLD": 0.1341176470588235,
    "XPL": 0.3329411764705882,
    "EIGEN": 0.3329411764705882,
    "PUMP": 0.05
  },
  "alerta_nivel": "VERDE",
  "alerta_detalles": {
    "VVV": {
      "nivel": "VERDE",
      "score": 2,
      "funding": 0.0013
    },
    "LIT": {
      "nivel": "VERDE",
      "score": 1,
      "funding": 0.0013
    },
    "GRASS": {
      "nivel": "VERDE",
      "score": 0,
      "funding": 0.0065
    },
    "WLD": {
      "nivel": "VERDE",
      "score": 1,
      "funding": 0.0013
    },
    "XPL": {
      "nivel": "VERDE",
      "score": 1,
      "funding": 0.0013
    },
    "EIGEN": {
      "nivel": "VERDE",
      "score": 0,
      "funding": 0.0013
    },
    "PUMP": {
      "nivel": "VERDE",
      "score": 0,
      "funding": 0.0013
    }
  },
  "watchlist": [
    {
      "coin": "BLUR",
      "vol_ratio": 14.42,
      "mov": 0.29
    },
    {
      "coin": "BANANA",
      "vol_ratio": 2.62,
      "mov": 0.05
    }
  ],
  "updated": "2026-07-07T16:34:01.951189+00:00"
}