{
  "roi": 61.64,
  "cycle": 139,
  "trades": 4305,
  "wr": 55.4,
  "grids": {
    "VVV": {
      "center": 10.801,
      "pnl": 117.35
    },
    "LIT": {
      "center": 2.5135,
      "pnl": 82.35
    },
    "GRASS": {
      "center": 0.46207,
      "pnl": 71.36
    },
    "WLD": {
      "center": 0.3909,
      "pnl": 106.49
    },
    "XPL": {
      "center": 0.10315,
      "pnl": 82.1
    },
    "EIGEN": {
      "center": 0.2287,
      "pnl": 99.51
    },
    "PUMP": {
      "center": 0.001603,
      "pnl": 57.28
    }
  },
  "pesos": {
    "VVV": 0.14285714285714285,
    "LIT": 0.14285714285714285,
    "GRASS": 0.14285714285714285,
    "WLD": 0.14285714285714285,
    "XPL": 0.14285714285714285,
    "EIGEN": 0.14285714285714285,
    "PUMP": 0.14285714285714285
  },
  "alerta_nivel": "AMBER",
  "alerta_detalles": {
    "VVV": {
      "nivel": "VERDE",
      "score": 1,
      "funding": 0.0013
    },
    "LIT": {
      "nivel": "VERDE",
      "score": 0,
      "funding": 0.0013
    },
    "GRASS": {
      "nivel": "AMBER",
      "score": 3,
      "funding": 0.0013
    },
    "WLD": {
      "nivel": "VERDE",
      "score": 0,
      "funding": 0.0013
    },
    "XPL": {
      "nivel": "VERDE",
      "score": 0,
      "funding": 0.0013
    },
    "EIGEN": {
      "nivel": "VERDE",
      "score": 0,
      "funding": 0.0013
    },
    "PUMP": {
      "nivel": "VERDE",
      "score": 0,
      "funding": 0.0013
    }
  },
  "watchlist": [
    {
      "coin": "BLUR",
      "vol_ratio": 14.44,
      "mov": 0.29
    }
  ],
  "updated": "2026-07-07T19:56:52.491957+00:00"
}