{
  "roi": 82.61,
  "cycle": 291,
  "trades": 10001,
  "wr": 40.2,
  "grids": {
    "VVV": {
      "center": 11.518,
      "pnl": -34.59
    },
    "LIT": {
      "center": 2.4111,
      "pnl": 26.44
    },
    "GRASS": {
      "center": 0.47754,
      "pnl": 145.54
    },
    "WLD": {
      "center": 0.40276,
      "pnl": 90.52
    },
    "XPL": {
      "center": 0.10327,
      "pnl": 277.57
    },
    "EIGEN": {
      "center": 0.2209,
      "pnl": 197.1
    },
    "PUMP": {
      "center": 0.001559,
      "pnl": 123.54
    }
  },
  "pesos": {
    "VVV": 0.05,
    "LIT": 0.23678160919540225,
    "GRASS": 0.05,
    "WLD": 0.05,
    "XPL": 0.1396551724137931,
    "EIGEN": 0.23678160919540225,
    "PUMP": 0.23678160919540225
  },
  "alerta_nivel": "VERDE",
  "alerta_detalles": {
    "VVV": {
      "nivel": "VERDE",
      "score": 0,
      "funding": 0.0013
    },
    "LIT": {
      "nivel": "VERDE",
      "score": 0,
      "funding": 0.0013
    },
    "GRASS": {
      "nivel": "VERDE",
      "score": 1,
      "funding": 0.0013
    },
    "WLD": {
      "nivel": "VERDE",
      "score": 0,
      "funding": 0.0006
    },
    "XPL": {
      "nivel": "VERDE",
      "score": 1,
      "funding": 0.0013
    },
    "EIGEN": {
      "nivel": "VERDE",
      "score": 0,
      "funding": 0.0013
    },
    "PUMP": {
      "nivel": "VERDE",
      "score": 1,
      "funding": 0.0013
    }
  },
  "watchlist": [
    {
      "coin": "BLUR",
      "vol_ratio": 6.41,
      "mov": 0.13
    }
  ],
  "updated": "2026-07-08T02:53:18.504721+00:00"
}