{
  "roi": 251.4,
  "cycle": 239,
  "trades": 7308,
  "wr": 73.1,
  "grids": {
    "VVV": {
      "center": 10.627,
      "pnl": 386.1
    },
    "LIT": {
      "center": 2.4461,
      "pnl": 362.51
    },
    "GRASS": {
      "center": 0.34849,
      "pnl": 421.82
    },
    "WLD": {
      "center": 0.37893,
      "pnl": 325.56
    },
    "XPL": {
      "center": 0.094415,
      "pnl": 384.85
    },
    "EIGEN": {
      "center": 0.2211,
      "pnl": 326.93
    },
    "PUMP": {
      "center": 0.001564,
      "pnl": 306.23
    }
  },
  "pesos": {
    "VVV": 0.14285714285714285,
    "LIT": 0.14285714285714285,
    "GRASS": 0.14285714285714285,
    "WLD": 0.14285714285714285,
    "XPL": 0.14285714285714285,
    "EIGEN": 0.14285714285714285,
    "PUMP": 0.14285714285714285
  },
  "alerta_nivel": "AMBER",
  "alerta_detalles": {
    "VVV": {
      "nivel": "VERDE",
      "score": 0,
      "funding": 0.0013
    },
    "LIT": {
      "nivel": "VERDE",
      "score": 0,
      "funding": 0.0013
    },
    "GRASS": {
      "nivel": "AMBER",
      "score": 3,
      "funding": 0.0013
    },
    "WLD": {
      "nivel": "VERDE",
      "score": 0,
      "funding": 0.0006
    },
    "XPL": {
      "nivel": "VERDE",
      "score": 1,
      "funding": 0.0013
    },
    "EIGEN": {
      "nivel": "VERDE",
      "score": 1,
      "funding": 0.0013
    },
    "PUMP": {
      "nivel": "VERDE",
      "score": 1,
      "funding": 0.0013
    }
  },
  "watchlist": [
    {
      "coin": "BLUR",
      "vol_ratio": 2.19,
      "mov": 0.04
    }
  ],
  "updated": "2026-07-08T05:54:48.466182+00:00"
}