{
  "roi": 9.97,
  "cycle": 95,
  "trades": 3103,
  "wr": 31.7,
  "grids": {
    "VVV": {
      "center": 11.518,
      "pnl": 41.56
    },
    "LIT": {
      "center": 2.4111,
      "pnl": -3.99
    },
    "GRASS": {
      "center": 0.47754,
      "pnl": -14.97
    },
    "WLD": {
      "center": 0.40276,
      "pnl": 49.35
    },
    "XPL": {
      "center": 0.10327,
      "pnl": 8.43
    },
    "EIGEN": {
      "center": 0.2209,
      "pnl": 28.11
    },
    "PUMP": {
      "center": 0.001559,
      "pnl": -8.76
    }
  },
  "pesos": {
    "VVV": 0.05,
    "LIT": 0.05,
    "GRASS": 0.05,
    "WLD": 0.37499999999999994,
    "XPL": 0.05,
    "EIGEN": 0.37499999999999994,
    "PUMP": 0.05
  },
  "alerta_nivel": "VERDE",
  "alerta_detalles": {
    "VVV": {
      "nivel": "VERDE",
      "score": 0,
      "funding": 0.0026
    },
    "LIT": {
      "nivel": "VERDE",
      "score": 0,
      "funding": 0.0013
    },
    "GRASS": {
      "nivel": "VERDE",
      "score": 0,
      "funding": 0.0081
    },
    "WLD": {
      "nivel": "VERDE",
      "score": 0,
      "funding": 0.0
    },
    "XPL": {
      "nivel": "VERDE",
      "score": 0,
      "funding": 0.0013
    },
    "EIGEN": {
      "nivel": "VERDE",
      "score": 0,
      "funding": 0.0013
    },
    "PUMP": {
      "nivel": "VERDE",
      "score": 0,
      "funding": 0.0013
    }
  },
  "watchlist": [
    {
      "coin": "BLUR",
      "vol_ratio": 31.68,
      "mov": 0.63
    }
  ],
  "updated": "2026-07-07T12:28:40.187561+00:00"
}